MANIFEST.in
README.rst
setup.cfg
setup.py
src/adminschUtils/__init__.py
src/adminschUtils.egg-info/PKG-INFO
src/adminschUtils.egg-info/SOURCES.txt
src/adminschUtils.egg-info/dependency_links.txt
src/adminschUtils.egg-info/not-zip-safe
src/adminschUtils.egg-info/requires.txt
src/adminschUtils.egg-info/top_level.txt
src/adminschUtils/AAA/__init__.py
src/adminschUtils/AAA/accounting.py
src/adminschUtils/AAA/authentication.py
src/adminschUtils/AAA/authorization.py
src/adminschUtils/config/Config.py
src/adminschUtils/config/__init__.py
src/adminschUtils/config/schema.py
src/adminschUtils/connections/__init__.py
src/adminschUtils/connections/base.py
src/adminschUtils/connections/httpclient.py
src/adminschUtils/connections/oauthclient.py
src/adminschUtils/connections/utils.py
src/adminschUtils/connections/zookeeper.py
src/adminschUtils/sphinx/__init__.py
src/adminschUtils/webserver/__init__.py
src/adminschUtils/webserver/models.py
src/adminschUtils/webserver/webserver.py