Metadata-Version: 1.0
Name: adminschUtils
Version: 0.2.5
Summary: Collections of tools for Admin.sch
Home-page: https://gitlab.sch.bme.hu/AdminSCH/utils
Author: Daniel Kiss
Author-email: daniel.kiss@kszk.bme.hu
License: GPLv3
Platform: UNKNOWN
